drawlogo/__init__.py
drawlogo/__main__.py
drawlogo/cli.py
drawlogo/version.py
drawlogo/letters/A.svg
drawlogo/letters/C.svg
drawlogo/letters/G.svg
drawlogo/letters/T.svg
drawlogo-1.0.6.dist-info/METADATA
drawlogo-1.0.6.dist-info/WHEEL
drawlogo-1.0.6.dist-info/entry_points.txt
drawlogo-1.0.6.dist-info/top_level.txt
drawlogo-1.0.6.dist-info/RECORD
