Metadata-Version: 2.1
Name: drawlogo
Version: 1.0.6
Home-page: https://github.com/autosome-org/draw_motif_logo
Author: Sergey Abramov, Alexandr Boytsov
Author-email: aswq22013@gmail.com
Requires-Python: >=3.6
Requires-Dist: docopt (>=0.6.2)
Requires-Dist: numpy (>=1.18.0)
Requires-Dist: schema (>=0.7.2)
Requires-Dist: svgutils (==0.3.1)
Requires-Dist: contextlib2 (>=0.5.5)
Provides-Extra: dev
Requires-Dist: wheel ; extra == 'dev'
Requires-Dist: twine ; extra == 'dev'
Requires-Dist: setuptools-scm ; extra == 'dev'
